onedevcommonfileextractor/ExtractorFile.py
onedevcommonfileextractor/__init__.py
onedevcommonfileextractor/azure/AzureOpenAIService.py
onedevcommonfileextractor/azure/__init__.py
onedevcommonfileextractor/docs/AZURE_OPENAI_GUIDE.md
onedevcommonfileextractor/docs/EXTRACAO_DUPLA_GUIDE.md
onedevcommonfileextractor/docs/GOOGLE_API_SETUP.md
onedevcommonfileextractor/docs/PDF_EXTRACTION_GUIDE.md
onedevcommonfileextractor/docs/TABELAS_PDF_GUIDE.md
onedevcommonfileextractor/output/JSONGenerator.py
onedevcommonfileextractor/output/__init__.py
onedevcommonfileextractor/pdf/PDFExtractor.py
onedevcommonfileextractor/pdf/TableExtractor.py
onedevcommonfileextractor/pdf/__init__.py
onedevcommonfileextractor/storage/JobSphereOCIObjectStorage.py
onedevcommonfileextractor/storage/StorageService.py
onedevcommonfileextractor/storage/oci/config
onedevcommonfileextractor/storage/oci/oci_api_key.pem
onedevcommonfileextractor-1.0.7.dist-info/METADATA
onedevcommonfileextractor-1.0.7.dist-info/WHEEL
onedevcommonfileextractor-1.0.7.dist-info/RECORD
