Metadata-Version: 2.3
Name: onedevcommonfileextractor
Version: 1.0.7
Summary: Ferramenta para extração de conteúdo de arquivos
Author: Renan
Author-email: renan.cardeal@ufly.com.br
Requires-Python: >=3.13,<4.0
Classifier: Programming Language :: Python :: 3
Classifier: Programming Language :: Python :: 3.13
Requires-Dist: Pillow (>=10.2.0,<11.0.0)
Requires-Dist: PyMuPDF (>=1.24.0,<2.0.0)
Requires-Dist: chromadb (==0.5.18)
Requires-Dist: cryptography (>=44.0.0,<45.0.0)
Requires-Dist: grpcio (>=1.68.1,<2.0.0)
Requires-Dist: grpcio-tools (>=1.68.1,<2.0.0)
Requires-Dist: langchain (>=0.3.20,<0.4.0)
Requires-Dist: langchain-chroma (>=0.2.2,<0.3.0)
Requires-Dist: langchain-google-genai (>=2.0.11,<3.0.0)
Requires-Dist: langgraph (>=0.3.6,<0.4.0)
Requires-Dist: oci (>=2.141.0,<3.0.0)
Requires-Dist: opencv-python (>=4.9.0,<5.0.0)
Requires-Dist: openpyxl (>=3.1.5,<4.0.0)
Requires-Dist: pandas (>=2.2.3,<3.0.0)
Requires-Dist: pycryptodome (>=3.21.0,<4.0.0)
Requires-Dist: pytesseract (>=0.3.10,<0.4.0)
Requires-Dist: python-dotenv (>=1.0.1,<2.0.0)
Requires-Dist: requests (>=2.32.3,<3.0.0)
Requires-Dist: sendgrid (>=6.11.0,<7.0.0)
Requires-Dist: xlsxwriter (>=3.2.0,<4.0.0)
